logspam/__init__.py
logspam/bisect.py
logspam/bugzilla.py
logspam/cache.py
logspam/cli.py
logspam/cli_entry.py
logspam/logs.py
logspam/mach_interface.py
logspam/report.py
mozilla_log_spam-0.1.4.dist-info/LICENSE
mozilla_log_spam-0.1.4.dist-info/METADATA
mozilla_log_spam-0.1.4.dist-info/WHEEL
mozilla_log_spam-0.1.4.dist-info/entry_points.txt
mozilla_log_spam-0.1.4.dist-info/top_level.txt
mozilla_log_spam-0.1.4.dist-info/RECORD
