Metadata-Version: 2.1
Name: mozilla-log-spam
Version: 0.1.4
Summary: Mozilla test log spam classifier
Home-page: https://github.com/EricRahm/log-spam-hell
Author: Eric Rahm
Author-email: erahm@mozilla.com
License: MPL 2.0
Download-URL: https://github.com/EricRahm/log-spam-hell/tarball/0.1.4
Platform: UNKNOWN
Classifier: License :: OSI Approved :: Mozilla Public License 2.0 (MPL 2.0)
Requires-Dist: mozregression (<4.1,>=4.0)
Requires-Dist: requests (<2.25,>=2.24)
Requires-Dist: treeherder-client (<5.1,>=5.0)
